pyvpt2/__init__.py
pyvpt2/constants.py
pyvpt2/fermi_solver.py
pyvpt2/quartic.py
pyvpt2/schema.py
pyvpt2/task_base.py
pyvpt2/task_planner.py
pyvpt2/vpt2.py
pyvpt2/tests/__init__.py
pyvpt2/tests/test_fermi_solver.py
pyvpt2/tests/test_h2co.py
pyvpt2/tests/test_h2o.py
pyvpt2/tests/test_h2o_cbs.py
pyvpt2/tests/test_h2o_multilevel.py
pyvpt2/tests/test_h2o_qcng.py
pyvpt2/tests/test_h2o_snowflake.py
pyvpt2/tests/test_h2o_snowflake2.py
pyvpt2/tests/test_hcn.py
pyvpt2/tests/test_hf.py
pyvpt2/tests/test_polyad.py
pyvpt2-0.1.2.dist-info/LICENSE
pyvpt2-0.1.2.dist-info/METADATA
pyvpt2-0.1.2.dist-info/WHEEL
pyvpt2-0.1.2.dist-info/top_level.txt
pyvpt2-0.1.2.dist-info/RECORD
