Metadata-Version: 2.1
Name: pyvpt2
Version: 0.1.2
Summary: Package to calculate VPT2 anharmonic frequencies.
Author-email: Philip Nelson <pmnelson@gatech.edu>
License: BSD-3-Clause
Requires-Python: >=3.8
License-File: LICENSE
